README.md
setup.py
src/spotibar/__init__.py
src/spotibar/client.py
src/spotibar/config_helper.py
src/spotibar/popups.py
src/spotibar.egg-info/PKG-INFO
src/spotibar.egg-info/SOURCES.txt
src/spotibar.egg-info/dependency_links.txt
src/spotibar.egg-info/entry_points.txt
src/spotibar.egg-info/requires.txt
src/spotibar.egg-info/top_level.txt