Metadata-Version: 1.2
Name: spotibar
Version: 0.1.3
Summary: Spotify plugin for Polybar
Home-page: https://github.com/conor-f/spotibar
License: UNKNOWN
Platform: UNKNOWN
Requires-Python: >=3.6
